buf/validate/validate_pb2.py
buf/validate/validate_pb2.pyi
buf/validate/validate_pb2_grpc.py
cerbos-0.14.0.dist-info/METADATA
cerbos-0.14.0.dist-info/WHEEL
cerbos-0.14.0.dist-info/entry_points.txt
cerbos-0.14.0.dist-info/licenses/LICENSE
cerbos/__init__.py
cerbos/audit/v1/audit_pb2.py
cerbos/audit/v1/audit_pb2.pyi
cerbos/audit/v1/audit_pb2_grpc.py
cerbos/cloud/apikey/v1/apikey_pb2.py
cerbos/cloud/apikey/v1/apikey_pb2.pyi
cerbos/cloud/apikey/v1/apikey_pb2_grpc.py
cerbos/cloud/bootstrap/v1/bootstrap_pb2.py
cerbos/cloud/bootstrap/v1/bootstrap_pb2.pyi
cerbos/cloud/bootstrap/v1/bootstrap_pb2_grpc.py
cerbos/cloud/bundle/v1/bundle_pb2.py
cerbos/cloud/bundle/v1/bundle_pb2.pyi
cerbos/cloud/bundle/v1/bundle_pb2_grpc.py
cerbos/cloud/bundle/v2/bundle_pb2.py
cerbos/cloud/bundle/v2/bundle_pb2.pyi
cerbos/cloud/bundle/v2/bundle_pb2_grpc.py
cerbos/cloud/epdp/v1/epdp_pb2.py
cerbos/cloud/epdp/v1/epdp_pb2.pyi
cerbos/cloud/epdp/v1/epdp_pb2_grpc.py
cerbos/cloud/logs/v1/logs_pb2.py
cerbos/cloud/logs/v1/logs_pb2.pyi
cerbos/cloud/logs/v1/logs_pb2_grpc.py
cerbos/cloud/pdp/v1/pdp_pb2.py
cerbos/cloud/pdp/v1/pdp_pb2.pyi
cerbos/cloud/pdp/v1/pdp_pb2_grpc.py
cerbos/cloud/store/v1/store_pb2.py
cerbos/cloud/store/v1/store_pb2.pyi
cerbos/cloud/store/v1/store_pb2_grpc.py
cerbos/effect/v1/effect_pb2.py
cerbos/effect/v1/effect_pb2.pyi
cerbos/effect/v1/effect_pb2_grpc.py
cerbos/engine/v1/engine_pb2.py
cerbos/engine/v1/engine_pb2.pyi
cerbos/engine/v1/engine_pb2_grpc.py
cerbos/policy/v1/policy_pb2.py
cerbos/policy/v1/policy_pb2.pyi
cerbos/policy/v1/policy_pb2_grpc.py
cerbos/py.typed
cerbos/request/v1/request_pb2.py
cerbos/request/v1/request_pb2.pyi
cerbos/request/v1/request_pb2_grpc.py
cerbos/response/v1/response_pb2.py
cerbos/response/v1/response_pb2.pyi
cerbos/response/v1/response_pb2_grpc.py
cerbos/schema/v1/schema_pb2.py
cerbos/schema/v1/schema_pb2.pyi
cerbos/schema/v1/schema_pb2_grpc.py
cerbos/sdk/__init__.py
cerbos/sdk/_async/__init__.py
cerbos/sdk/_async/_grpc.py
cerbos/sdk/_async/_http.py
cerbos/sdk/_async/_hub/__init__.py
cerbos/sdk/_async/_hub/_auth.py
cerbos/sdk/_async/_hub/_client.py
cerbos/sdk/_async/_hub/_interceptors.py
cerbos-0.14.0.dist-info/RECORD
