Metadata-Version: 2.1
Name: cerbos
Version: 0.14.0
Summary: SDK for working with Cerbos: an open core, language-agnostic, scalable authorization solution
Author-Email: Cerbos Developers <sdk+python@cerbos.dev>
License: Apache-2.0
Classifier: Development Status :: 4 - Beta
Classifier: Intended Audience :: Developers
Classifier: Topic :: Security
Classifier: Topic :: Software Development :: Libraries
Project-URL: Homepage, https://cerbos.dev
Requires-Python: >=3.9
Requires-Dist: dataclasses-json>=0.5.7
Requires-Dist: requests-toolbelt>=0.9.1
Requires-Dist: httpx[http2]>=0.22.0
Requires-Dist: anyio>=3.6.1
Requires-Dist: tenacity>=8.1.0
Requires-Dist: grpcio-tools>=1.54.2
Requires-Dist: types-protobuf>=4.24.0.1
Requires-Dist: protoc-gen-openapiv2>=0.0.1
Requires-Dist: googleapis-common-protos>=1.62.0
Requires-Dist: protobuf>=6.31.0
Requires-Dist: grpcio-status>=1.73.0
Requires-Dist: circuitbreaker>=2.1.3
Provides-Extra: testcontainers
Requires-Dist: testcontainers>=3.5.3; extra == "testcontainers"
